{"regency_code": "P009R002", "districts": [{"district_code": "P009R002D001", "regency_code": "P009R002", "district": "Batujajar"}, {"district_code": "P009R002D002", "regency_code": "P009R002", "district": "Cihampelas"}, {"district_code": "P009R002D003", "regency_code": "P009R002", "district": "Cikalongwetan"}, {"district_code": "P009R002D004", "regency_code": "P009R002", "district": "Cililin"}, {"district_code": "P009R002D005", "regency_code": "P009R002", "district": "Cipatat"}, {"district_code": "P009R002D006", "regency_code": "P009R002", "district": "Cipeundeuy"}, {"district_code": "P009R002D007", "regency_code": "P009R002", "district": "Cipongkor"}, {"district_code": "P009R002D008", "regency_code": "P009R002", "district": "Cisarua"}, {"district_code": "P009R002D009", "regency_code": "P009R002", "district": "Gununghalu"}, {"district_code": "P009R002D010", "regency_code": "P009R002", "district": "Lembang"}, {"district_code": "P009R002D011", "regency_code": "P009R002", "district": "Ngamprah"}, {"district_code": "P009R002D012", "regency_code": "P009R002", "district": "Padalarang"}, {"district_code": "P009R002D013", "regency_code": "P009R002", "district": "Parongpong"}, {"district_code": "P009R002D014", "regency_code": "P009R002", "district": "Rongga"}, {"district_code": "P009R002D015", "regency_code": "P009R002", "district": "Saguling"}, {"district_code": "P009R002D016", "regency_code": "P009R002", "district": "Sindangkerta"}]}