{"regency_code": "P014R007", "districts": [{"district_code": "P014R007D001", "regency_code": "P014R007", "district": "Arut Selatan"}, {"district_code": "P014R007D002", "regency_code": "P014R007", "district": "Arut Utara"}, {"district_code": "P014R007D003", "regency_code": "P014R007", "district": "Kotawaringin Lama"}, {"district_code": "P014R007D004", "regency_code": "P014R007", "district": "Kumai"}, {"district_code": "P014R007D005", "regency_code": "P014R007", "district": "Pangkalan Banteng"}, {"district_code": "P014R007D006", "regency_code": "P014R007", "district": "Pangkalan Lada"}]}