{"regency_code": "P030R001", "districts": [{"district_code": "P030R001D001", "regency_code": "P030R001", "district": "Bandar Laksamana"}, {"district_code": "P030R001D002", "regency_code": "P030R001", "district": "Bantan"}, {"district_code": "P030R001D003", "regency_code": "P030R001", "district": "Bathin Solapan"}, {"district_code": "P030R001D004", "regency_code": "P030R001", "district": "Bengkalis"}, {"district_code": "P030R001D005", "regency_code": "P030R001", "district": "Bukit Batu"}, {"district_code": "P030R001D006", "regency_code": "P030R001", "district": "Mandau"}, {"district_code": "P030R001D007", "regency_code": "P030R001", "district": "Pinggir"}, {"district_code": "P030R001D008", "regency_code": "P030R001", "district": "Rupat"}, {"district_code": "P030R001D009", "regency_code": "P030R001", "district": "Rupat Utara"}, {"district_code": "P030R001D010", "regency_code": "P030R001", "district": "Siak Kecil"}, {"district_code": "P030R001D011", "regency_code": "P030R001", "district": "Talang Muandau"}]}