{"district_code": "P001R002D009", "villages": [{"village_code": "P001R002D009V0001", "district_code": "P001R002D009", "village": "Adan", "postal_code": [23768]}, {"village_code": "P001R002D009V0002", "district_code": "P001R002D009", "village": "Bineh Krueng", "postal_code": [23768]}, {"village_code": "P001R002D009V0003", "district_code": "P001R002D009", "village": "Blang Padang", "postal_code": [23768]}, {"village_code": "P001R002D009V0004", "district_code": "P001R002D009", "village": "Drien Jalo", "postal_code": [23768]}, {"village_code": "P001R002D009V0005", "district_code": "P001R002D009", "village": "Drien Kipah", "postal_code": [23768]}, {"village_code": "P001R002D009V0006", "district_code": "P001R002D009", "village": "Gunong Cut", "postal_code": [23768]}, {"village_code": "P001R002D009V0007", "district_code": "P001R002D009", "village": "Ie Lhob", "postal_code": [23768]}, {"village_code": "P001R002D009V0008", "district_code": "P001R002D009", "village": "Kuta Bak Drien", "postal_code": [23768]}, {"village_code": "P001R002D009V0009", "district_code": "P001R002D009", "village": "Mesjid", "postal_code": [23768]}, {"village_code": "P001R002D009V0010", "district_code": "P001R002D009", "village": "Padang Bak Jeumpa", "postal_code": [23768]}, {"village_code": "P001R002D009V0011", "district_code": "P001R002D009", "village": "Padang Bak Jok", "postal_code": [23768]}, {"village_code": "P001R002D009V0012", "district_code": "P001R002D009", "village": "Padang Kawa", "postal_code": [23768]}, {"village_code": "P001R002D009V0013", "district_code": "P001R002D009", "village": "Pante Geulumpang", "postal_code": [23768]}, {"village_code": "P001R002D009V0014", "district_code": "P001R002D009", "village": "Suak Labu", "postal_code": [23768]}, {"village_code": "P001R002D009V0015", "district_code": "P001R002D009", "village": "Suak Nibong", "postal_code": [23768]}]}