{"district_code": "P001R006D001", "villages": [{"village_code": "P001R006D001V0001", "district_code": "P001R006D001", "village": "Butar", "postal_code": [24792]}, {"village_code": "P001R006D001V0002", "district_code": "P001R006D001", "village": "Danau Bungara", "postal_code": [24792]}, {"village_code": "P001R006D001V0003", "district_code": "P001R006D001", "village": "Ladang Bisik", "postal_code": [24792]}, {"village_code": "P001R006D001V0004", "district_code": "P001R006D001", "village": "Lapahan Buaya", "postal_code": [24792]}, {"village_code": "P001R006D001V0005", "district_code": "P001R006D001", "village": "Lentong", "postal_code": [24792]}, {"village_code": "P001R006D001V0006", "district_code": "P001R006D001", "village": "Muara Pea", "postal_code": [24792]}, {"village_code": "P001R006D001V0007", "district_code": "P001R006D001", "village": "Pea Jambu", "postal_code": [24792]}, {"village_code": "P001R006D001V0008", "district_code": "P001R006D001", "village": "Samar Dua", "postal_code": [24792]}, {"village_code": "P001R006D001V0009", "district_code": "P001R006D001", "village": "Sumber Mukti", "postal_code": [24792]}]}