{"district_code": "P006R002D002", "villages": [{"village_code": "P006R002D002V0001", "district_code": "P006R002D002", "village": "Cideng", "postal_code": [10150]}, {"village_code": "P006R002D002V0002", "district_code": "P006R002D002", "village": "Duri Pulo", "postal_code": [10140]}, {"village_code": "P006R002D002V0003", "district_code": "P006R002D002", "village": "Gambir", "postal_code": [10110]}, {"village_code": "P006R002D002V0004", "district_code": "P006R002D002", "village": "Kebon Kelapa", "postal_code": [10120]}, {"village_code": "P006R002D002V0005", "district_code": "P006R002D002", "village": "Petojo Selatan", "postal_code": [10160]}, {"village_code": "P006R002D002V0006", "district_code": "P006R002D002", "village": "Petojo Utara", "postal_code": [10130]}]}