{"district_code": "P009R002D013", "villages": [{"village_code": "P009R002D013V0001", "district_code": "P009R002D013", "village": "Cigugurgirang", "postal_code": [40559]}, {"village_code": "P009R002D013V0002", "district_code": "P009R002D013", "village": "Cihanjuang", "postal_code": [40559]}, {"village_code": "P009R002D013V0003", "district_code": "P009R002D013", "village": "Cihanjuangrahayu", "postal_code": [40559]}, {"village_code": "P009R002D013V0004", "district_code": "P009R002D013", "village": "Cihideung", "postal_code": [40559]}, {"village_code": "P009R002D013V0005", "district_code": "P009R002D013", "village": "Ciwaruga", "postal_code": [40559]}, {"village_code": "P009R002D013V0006", "district_code": "P009R002D013", "village": "Karyawangi", "postal_code": [40559]}, {"village_code": "P009R002D013V0007", "district_code": "P009R002D013", "village": "Sariwangi", "postal_code": [40559]}]}