{"district_code": "P009R021D018", "villages": [{"village_code": "P009R021D018V0001", "district_code": "P009R021D018", "village": "Indihiang", "postal_code": [46151]}, {"village_code": "P009R021D018V0002", "district_code": "P009R021D018", "village": "Panyingkiran", "postal_code": [46411]}, {"village_code": "P009R021D018V0003", "district_code": "P009R021D018", "village": "Parakannyasag", "postal_code": [46151]}, {"village_code": "P009R021D018V0004", "district_code": "P009R021D018", "village": "Sirnagalih", "postal_code": [46151]}, {"village_code": "P009R021D018V0005", "district_code": "P009R021D018", "village": "Sukamaju Kaler", "postal_code": [46151]}, {"village_code": "P009R021D018V0006", "district_code": "P009R021D018", "village": "Sukamaju Kidul", "postal_code": [46151]}]}