{"district_code": "P009R021D032", "villages": [{"village_code": "P009R021D032V0001", "district_code": "P009R021D032", "village": "Barumekar", "postal_code": [46189]}, {"village_code": "P009R021D032V0002", "district_code": "P009R021D032", "village": "Burujuljaya", "postal_code": [46189]}, {"village_code": "P009R021D032V0003", "district_code": "P009R021D032", "village": "Cibanteng", "postal_code": [46189]}, {"village_code": "P009R021D032V0004", "district_code": "P009R021D032", "village": "Cibungur", "postal_code": [46189]}, {"village_code": "P009R021D032V0005", "district_code": "P009R021D032", "village": "Cigunung", "postal_code": [46189]}, {"village_code": "P009R021D032V0006", "district_code": "P009R021D032", "village": "Girikencana", "postal_code": [46189]}, {"village_code": "P009R021D032V0007", "district_code": "P009R021D032", "village": "Karyabakti", "postal_code": [46189]}, {"village_code": "P009R021D032V0008", "district_code": "P009R021D032", "village": "Parungponteng", "postal_code": [46189]}]}