{"district_code": "P011R015D020", "villages": [{"village_code": "P011R015D020V0001", "district_code": "P011R015D020", "village": "Babadan", "postal_code": [65164]}, {"village_code": "P011R015D020V0002", "district_code": "P011R015D020", "village": "Balesari", "postal_code": [65164]}, {"village_code": "P011R015D020V0003", "district_code": "P011R015D020", "village": "Banjarsari", "postal_code": [65164]}, {"village_code": "P011R015D020V0004", "district_code": "P011R015D020", "village": "Kesamben", "postal_code": [65164]}, {"village_code": "P011R015D020V0005", "district_code": "P011R015D020", "village": "Kranggan", "postal_code": [65164]}, {"village_code": "P011R015D020V0006", "district_code": "P011R015D020", "village": "Maguan", "postal_code": [65164]}, {"village_code": "P011R015D020V0007", "district_code": "P011R015D020", "village": "Ngajum", "postal_code": [65164]}, {"village_code": "P011R015D020V0008", "district_code": "P011R015D020", "village": "Ngasem", "postal_code": [65164]}, {"village_code": "P011R015D020V0009", "district_code": "P011R015D020", "village": "Palaan", "postal_code": [65164]}]}