{"district_code": "P012R013D003", "villages": [{"village_code": "P012R013D003V0001", "district_code": "P012R013D003", "village": "Bukit Batu", "postal_code": [79114]}, {"village_code": "P012R013D003V0002", "district_code": "P012R013D003", "village": "Condong", "postal_code": [79111]}, {"village_code": "P012R013D003V0003", "district_code": "P012R013D003", "village": "Jawa", "postal_code": [79116]}, {"village_code": "P012R013D003V0004", "district_code": "P012R013D003", "village": "Roban", "postal_code": [79112]}, {"village_code": "P012R013D003V0005", "district_code": "P012R013D003", "village": "Sekip Lama", "postal_code": [79113]}, {"village_code": "P012R013D003V0006", "district_code": "P012R013D003", "village": "Sungai Wie", "postal_code": [79115]}]}