{"district_code": "P013R010D002", "villages": [{"village_code": "P013R010D002V0001", "district_code": "P013R010D002", "village": "Argo Mulyo", "postal_code": [71572]}, {"village_code": "P013R010D002V0002", "district_code": "P013R010D002", "village": "Bintang Ara", "postal_code": [71572]}, {"village_code": "P013R010D002V0003", "district_code": "P013R010D002", "village": "Bumi Makmur", "postal_code": [71572]}, {"village_code": "P013R010D002V0004", "district_code": "P013R010D002", "village": "Burum", "postal_code": [71572]}, {"village_code": "P013R010D002V0005", "district_code": "P013R010D002", "village": "Dambung Raya", "postal_code": [71572]}, {"village_code": "P013R010D002V0006", "district_code": "P013R010D002", "village": "Hegarmanah", "postal_code": [71572]}, {"village_code": "P013R010D002V0007", "district_code": "P013R010D002", "village": "Panaan", "postal_code": [71572]}, {"village_code": "P013R010D002V0008", "district_code": "P013R010D002", "village": "Usih", "postal_code": [71572]}, {"village_code": "P013R010D002V0009", "district_code": "P013R010D002", "village": "Waling", "postal_code": [71572]}]}