{"district_code": "P019R001D015", "villages": [{"village_code": "P019R001D015V0001", "district_code": "P019R001D015", "village": "Baru", "postal_code": [35121]}, {"village_code": "P019R001D015V0002", "district_code": "P019R001D015", "village": "Kebon Jeruk", "postal_code": [35121]}, {"village_code": "P019R001D015V0003", "district_code": "P019R001D015", "village": "Sawah Brebes", "postal_code": [35124]}, {"village_code": "P019R001D015V0004", "district_code": "P019R001D015", "village": "Sawah Lama", "postal_code": [35125]}, {"village_code": "P019R001D015V0005", "district_code": "P019R001D015", "village": "Tanjung Agung", "postal_code": [35126]}]}