{"district_code": "P020R005D002", "villages": [{"village_code": "P020R005D002V0001", "district_code": "P020R005D002", "village": "Adodo Molu", "postal_code": [97462]}, {"village_code": "P020R005D002V0002", "district_code": "P020R005D002", "village": "Nurkat", "postal_code": [97462]}, {"village_code": "P020R005D002V0003", "district_code": "P020R005D002", "village": "Tutunametal", "postal_code": [97462]}, {"village_code": "P020R005D002V0004", "district_code": "P020R005D002", "village": "Wadankou", "postal_code": [97462]}, {"village_code": "P020R005D002V0005", "district_code": "P020R005D002", "village": "Wulmasa", "postal_code": [97462]}]}