{"district_code": "P020R010D008", "villages": [{"village_code": "P020R010D008V0001", "district_code": "P020R010D008", "village": "Ainena", "postal_code": [97592]}, {"village_code": "P020R010D008V0002", "district_code": "P020R010D008", "village": "Akatfadedo", "postal_code": [97592]}, {"village_code": "P020R010D008V0003", "district_code": "P020R010D008", "village": "Geser", "postal_code": [97592]}, {"village_code": "P020R010D008V0004", "district_code": "P020R010D008", "village": "Guli-Guli", "postal_code": [97592]}, {"village_code": "P020R010D008V0005", "district_code": "P020R010D008", "village": "Keffing", "postal_code": [97592]}, {"village_code": "P020R010D008V0006", "district_code": "P020R010D008", "village": "Kellu", "postal_code": [97592]}, {"village_code": "P020R010D008V0007", "district_code": "P020R010D008", "village": "Kilfura", "postal_code": [97592]}, {"village_code": "P020R010D008V0008", "district_code": "P020R010D008", "village": "Kiltay", "postal_code": [97592]}, {"village_code": "P020R010D008V0009", "district_code": "P020R010D008", "village": "Kilwaru", "postal_code": [97592]}, {"village_code": "P020R010D008V0010", "district_code": "P020R010D008", "village": "Kwawor Besar Ena", "postal_code": [97592]}, {"village_code": "P020R010D008V0011", "district_code": "P020R010D008", "village": "Kwawor Besar Witau", "postal_code": [97592]}, {"village_code": "P020R010D008V0012", "district_code": "P020R010D008", "village": "Kwawor Kecil Mata Ata", "postal_code": [97592]}, {"village_code": "P020R010D008V0013", "district_code": "P020R010D008", "village": "Kwawor Kecil Mata Wawa", "postal_code": [97592]}, {"village_code": "P020R010D008V0014", "district_code": "P020R010D008", "village": "Manggis", "postal_code": [97592]}, {"village_code": "P020R010D008V0015", "district_code": "P020R010D008", "village": "Mugusinis", "postal_code": [97592]}, {"village_code": "P020R010D008V0016", "district_code": "P020R010D008", "village": "Urung", "postal_code": [97592]}]}