{"district_code": "P023R003D005", "villages": [{"village_code": "P023R003D005V0001", "district_code": "P023R003D005", "village": "Mbongawani", "postal_code": [86313]}, {"village_code": "P023R003D005V0002", "district_code": "P023R003D005", "village": "Paupanda", "postal_code": [86315]}, {"village_code": "P023R003D005V0003", "district_code": "P023R003D005", "village": "Rukun Lima", "postal_code": [86314]}, {"village_code": "P023R003D005V0004", "district_code": "P023R003D005", "village": "Tanjung", "postal_code": [86316]}, {"village_code": "P023R003D005V0005", "district_code": "P023R003D005", "village": "Tetandara", "postal_code": [86316]}]}