{"district_code": "P023R006D010", "villages": [{"village_code": "P023R006D010V0001", "district_code": "P023R006D010", "village": "Fatumetan", "postal_code": [85373]}, {"village_code": "P023R006D010V0002", "district_code": "P023R006D010", "village": "Fatusuki", "postal_code": [85373]}, {"village_code": "P023R006D010V0003", "district_code": "P023R006D010", "village": "Leloboko", "postal_code": [85373]}, {"village_code": "P023R006D010V0004", "district_code": "P023R006D010", "village": "Lelogama", "postal_code": [85373]}, {"village_code": "P023R006D010V0005", "district_code": "P023R006D010", "village": "Oelbanu", "postal_code": [85373]}, {"village_code": "P023R006D010V0006", "district_code": "P023R006D010", "village": "Oh'aem", "postal_code": [85373]}, {"village_code": "P023R006D010V0007", "district_code": "P023R006D010", "village": "Oh'aem II", "postal_code": [85373]}]}