{"district_code": "P025R006D003", "villages": [{"village_code": "P025R006D003V0001", "district_code": "P025R006D003", "village": "Amutu", "postal_code": [98132]}, {"village_code": "P025R006D003V0002", "district_code": "P025R006D003", "village": "Irarutu III", "postal_code": [98132]}, {"village_code": "P025R006D003V0003", "district_code": "P025R006D003", "village": "Kasira", "postal_code": [98132]}, {"village_code": "P025R006D003V0004", "district_code": "P025R006D003", "village": "Nusei", "postal_code": [98132]}]}