{"district_code": "P026R003D030", "villages": [{"village_code": "P026R003D030V0001", "district_code": "P026R003D030", "village": "Gisim", "postal_code": [98427]}, {"village_code": "P026R003D030V0002", "district_code": "P026R003D030", "village": "Klajaring", "postal_code": [98427]}, {"village_code": "P026R003D030V0003", "district_code": "P026R003D030", "village": "Klasegun", "postal_code": [98427]}, {"village_code": "P026R003D030V0004", "district_code": "P026R003D030", "village": "Klasin", "postal_code": [98427]}, {"village_code": "P026R003D030V0005", "district_code": "P026R003D030", "village": "Majemau", "postal_code": [98427]}, {"village_code": "P026R003D030V0006", "district_code": "P026R003D030", "village": "Malamas", "postal_code": [98427]}, {"village_code": "P026R003D030V0007", "district_code": "P026R003D030", "village": "Segun", "postal_code": [98427]}, {"village_code": "P026R003D030V0008", "district_code": "P026R003D030", "village": "Waimlabat", "postal_code": [98427]}, {"village_code": "P026R003D030V0009", "district_code": "P026R003D030", "village": "Waimon", "postal_code": [98427]}]}