{"district_code": "P027R005D025", "villages": [{"village_code": "P027R005D025V0001", "district_code": "P027R005D025", "village": "Autpahik", "postal_code": [99426]}, {"village_code": "P027R005D025V0002", "district_code": "P027R005D025", "village": "Bomding", "postal_code": [99426]}, {"village_code": "P027R005D025V0003", "district_code": "P027R005D025", "village": "Honkuding", "postal_code": [99426]}, {"village_code": "P027R005D025V0004", "district_code": "P027R005D025", "village": "Okdilam", "postal_code": [99426]}, {"village_code": "P027R005D025V0005", "district_code": "P027R005D025", "village": "Okdunam", "postal_code": [99426]}, {"village_code": "P027R005D025V0006", "district_code": "P027R005D025", "village": "Okhaka", "postal_code": [99426]}, {"village_code": "P027R005D025V0007", "district_code": "P027R005D025", "village": "Okma", "postal_code": [99426]}, {"village_code": "P027R005D025V0008", "district_code": "P027R005D025", "village": "Okpa", "postal_code": [99426]}, {"village_code": "P027R005D025V0009", "district_code": "P027R005D025", "village": "Oktae", "postal_code": [99426]}, {"village_code": "P027R005D025V0010", "district_code": "P027R005D025", "village": "Paune", "postal_code": [99426]}, {"village_code": "P027R005D025V0011", "district_code": "P027R005D025", "village": "Tinibil", "postal_code": [99426]}, {"village_code": "P027R005D025V0012", "district_code": "P027R005D025", "village": "Tomka", "postal_code": [99426]}]}