{"district_code": "P027R007D032", "villages": [{"village_code": "P027R007D032V0001", "district_code": "P027R007D032", "village": "Asotapo", "postal_code": [99710]}, {"village_code": "P027R007D032V0002", "district_code": "P027R007D032", "village": "Haleroma", "postal_code": [99710]}, {"village_code": "P027R007D032V0003", "district_code": "P027R007D032", "village": "Hirin", "postal_code": [99710]}, {"village_code": "P027R007D032V0004", "district_code": "P027R007D032", "village": "Hugi Lokon", "postal_code": [99710]}, {"village_code": "P027R007D032V0005", "district_code": "P027R007D032", "village": "Ison", "postal_code": [99710]}, {"village_code": "P027R007D032V0006", "district_code": "P027R007D032", "village": "Muke", "postal_code": [99710]}, {"village_code": "P027R007D032V0007", "district_code": "P027R007D032", "village": "Notnarek", "postal_code": [99710]}, {"village_code": "P027R007D032V0008", "district_code": "P027R007D032", "village": "Pona", "postal_code": [99710]}, {"village_code": "P027R007D032V0009", "district_code": "P027R007D032", "village": "Samenage", "postal_code": [99710]}]}