{"district_code": "P031R001D003", "villages": [{"village_code": "P031R001D003V0001", "district_code": "P031R001D003", "village": "Bambangan", "postal_code": [91453]}, {"village_code": "P031R001D003V0002", "district_code": "P031R001D003", "village": "Kayuangin", "postal_code": [91453]}, {"village_code": "P031R001D003V0003", "district_code": "P031R001D003", "village": "Lamungang Batu", "postal_code": [91453]}, {"village_code": "P031R001D003V0004", "district_code": "P031R001D003", "village": "Lombang", "postal_code": [91453]}, {"village_code": "P031R001D003V0005", "district_code": "P031R001D003", "village": "Lombang Timur", "postal_code": [91453]}, {"village_code": "P031R001D003V0006", "district_code": "P031R001D003", "village": "Lombong", "postal_code": [91453]}, {"village_code": "P031R001D003V0007", "district_code": "P031R001D003", "village": "Lombong Timur", "postal_code": [91453]}, {"village_code": "P031R001D003V0008", "district_code": "P031R001D003", "village": "Maliaya", "postal_code": [91453]}, {"village_code": "P031R001D003V0009", "district_code": "P031R001D003", "village": "Malunda", "postal_code": [91453]}, {"village_code": "P031R001D003V0010", "district_code": "P031R001D003", "village": "Mekkatta", "postal_code": [91453]}, {"village_code": "P031R001D003V0011", "district_code": "P031R001D003", "village": "Mekkatta Selatan", "postal_code": [91453]}, {"village_code": "P031R001D003V0012", "district_code": "P031R001D003", "village": "Salutahongan", "postal_code": [91453]}]}