{"district_code": "P033R007D004", "villages": [{"village_code": "P033R007D004V0001", "district_code": "P033R007D004", "village": "Girimulya", "postal_code": [94968]}, {"village_code": "P033R007D004V0002", "district_code": "P033R007D004", "village": "Kolo Atas", "postal_code": [94968]}, {"village_code": "P033R007D004V0003", "district_code": "P033R007D004", "village": "Kolo Bawah", "postal_code": [94968]}, {"village_code": "P033R007D004V0004", "district_code": "P033R007D004", "village": "Lijo", "postal_code": [94968]}, {"village_code": "P033R007D004V0005", "district_code": "P033R007D004", "village": "Menyo'e", "postal_code": [94968]}, {"village_code": "P033R007D004V0006", "district_code": "P033R007D004", "village": "Momo", "postal_code": [94968]}, {"village_code": "P033R007D004V0007", "district_code": "P033R007D004", "village": "Pandauke", "postal_code": [94968]}, {"village_code": "P033R007D004V0008", "district_code": "P033R007D004", "village": "Parangisi", "postal_code": [94968]}, {"village_code": "P033R007D004V0009", "district_code": "P033R007D004", "village": "Sea", "postal_code": [94968]}, {"village_code": "P033R007D004V0010", "district_code": "P033R007D004", "village": "Tambale", "postal_code": [94968]}, {"village_code": "P033R007D004V0011", "district_code": "P033R007D004", "village": "Tananagaya", "postal_code": [94968]}, {"village_code": "P033R007D004V0012", "district_code": "P033R007D004", "village": "Tanasumpu", "postal_code": [94968]}, {"village_code": "P033R007D004V0013", "district_code": "P033R007D004", "village": "Uepakatu", "postal_code": [94968]}, {"village_code": "P033R007D004V0014", "district_code": "P033R007D004", "village": "Winangobino", "postal_code": [94968]}]}