{"district_code": "P035R013D006", "villages": [{"village_code": "P035R013D006V0001", "district_code": "P035R013D006", "village": "Basaan", "postal_code": [95999]}, {"village_code": "P035R013D006V0002", "district_code": "P035R013D006", "village": "Basaan Dua", "postal_code": [95999]}, {"village_code": "P035R013D006V0003", "district_code": "P035R013D006", "village": "Basaan Satu", "postal_code": [95999]}, {"village_code": "P035R013D006V0004", "district_code": "P035R013D006", "village": "Morea", "postal_code": [95999]}, {"village_code": "P035R013D006V0005", "district_code": "P035R013D006", "village": "Morea Satu", "postal_code": [95999]}, {"village_code": "P035R013D006V0006", "district_code": "P035R013D006", "village": "Ratatotok", "postal_code": [95999]}, {"village_code": "P035R013D006V0007", "district_code": "P035R013D006", "village": "Ratatotok Dua", "postal_code": [95999]}, {"village_code": "P035R013D006V0008", "district_code": "P035R013D006", "village": "Ratatotok Muara", "postal_code": [95999]}, {"village_code": "P035R013D006V0009", "district_code": "P035R013D006", "village": "Ratatotok Satu", "postal_code": [95999]}, {"village_code": "P035R013D006V0010", "district_code": "P035R013D006", "village": "Ratatotok Selatan", "postal_code": [95999]}, {"village_code": "P035R013D006V0011", "district_code": "P035R013D006", "village": "Ratatotok Tengah", "postal_code": [95999]}, {"village_code": "P035R013D006V0012", "district_code": "P035R013D006", "village": "Ratatotok Tenggara", "postal_code": [95999]}, {"village_code": "P035R013D006V0013", "district_code": "P035R013D006", "village": "Ratatotok Timur", "postal_code": [95999]}, {"village_code": "P035R013D006V0014", "district_code": "P035R013D006", "village": "Ratatotok Utara", "postal_code": [95999]}, {"village_code": "P035R013D006V0015", "district_code": "P035R013D006", "village": "Soyoan", "postal_code": [95999]}]}