{"district_code": "P037R013D006", "villages": [{"village_code": "P037R013D006V0001", "district_code": "P037R013D006", "village": "Mulya Sari", "postal_code": [32388]}, {"village_code": "P037R013D006V0002", "district_code": "P037R013D006", "village": "Petanggan", "postal_code": [32388]}, {"village_code": "P037R013D006V0003", "district_code": "P037R013D006", "village": "Purwodadi", "postal_code": [32388]}, {"village_code": "P037R013D006V0004", "district_code": "P037R013D006", "village": "Rejo Sari", "postal_code": [32388]}, {"village_code": "P037R013D006V0005", "district_code": "P037R013D006", "village": "Sari Guna", "postal_code": [32388]}, {"village_code": "P037R013D006V0006", "district_code": "P037R013D006", "village": "Sido Waluyo", "postal_code": [32388]}, {"village_code": "P037R013D006V0007", "district_code": "P037R013D006", "village": "Sri Mulyo", "postal_code": [32388]}, {"village_code": "P037R013D006V0008", "district_code": "P037R013D006", "village": "Sribudaya", "postal_code": [32388]}, {"village_code": "P037R013D006V0009", "district_code": "P037R013D006", "village": "Sugih Waras", "postal_code": [32388]}, {"village_code": "P037R013D006V0010", "district_code": "P037R013D006", "village": "Sukoharjo", "postal_code": [32388]}, {"village_code": "P037R013D006V0011", "district_code": "P037R013D006", "village": "Tulung Sari", "postal_code": [32388]}, {"village_code": "P037R013D006V0012", "district_code": "P037R013D006", "village": "Ulak Buntar", "postal_code": [32388]}]}