{"district_code": "P037R005D019", "villages": [{"village_code": "P037R005D019V0001", "district_code": "P037R005D019", "village": "Aremantai", "postal_code": [31355]}, {"village_code": "P037R005D019V0002", "district_code": "P037R005D019", "village": "Cahaya Alam", "postal_code": [31355]}, {"village_code": "P037R005D019V0003", "district_code": "P037R005D019", "village": "Danau Gerak", "postal_code": [31355]}, {"village_code": "P037R005D019V0004", "district_code": "P037R005D019", "village": "Datar Lebar", "postal_code": [31355]}, {"village_code": "P037R005D019V0005", "district_code": "P037R005D019", "village": "Pajar Bulan", "postal_code": [31355]}, {"village_code": "P037R005D019V0006", "district_code": "P037R005D019", "village": "Pelakat", "postal_code": [31355]}, {"village_code": "P037R005D019V0007", "district_code": "P037R005D019", "village": "Segamit", "postal_code": [31355]}, {"village_code": "P037R005D019V0008", "district_code": "P037R005D019", "village": "Siring Agung", "postal_code": [31355]}, {"village_code": "P037R005D019V0009", "district_code": "P037R005D019", "village": "Tanjung Agung", "postal_code": [31355]}, {"village_code": "P037R005D019V0010", "district_code": "P037R005D019", "village": "Tanjung Tiga", "postal_code": [31355]}]}