{"district_code": "P038R012D004", "villages": [{"village_code": "P038R012D004V0001", "district_code": "P038R012D004", "village": "Kelantan", "postal_code": [20881]}, {"village_code": "P038R012D004V0002", "district_code": "P038R012D004", "village": "Lubuk Kasih", "postal_code": [20881]}, {"village_code": "P038R012D004V0003", "district_code": "P038R012D004", "village": "Lubuk Kertang", "postal_code": [20881]}, {"village_code": "P038R012D004V0004", "district_code": "P038R012D004", "village": "Pangkalan Batu", "postal_code": [20881]}, {"village_code": "P038R012D004V0005", "district_code": "P038R012D004", "village": "Perlis", "postal_code": [20881]}, {"village_code": "P038R012D004V0006", "district_code": "P038R012D004", "village": "Sei Tualang", "postal_code": [20881]}, {"village_code": "P038R012D004V0007", "district_code": "P038R012D004", "village": "Tangkahan Durian", "postal_code": [20881]}]}