{"district_code": "P038R031D007", "villages": [{"village_code": "P038R031D007V0001", "district_code": "P038R031D007", "village": "Batu Nadua", "postal_code": [22472]}, {"village_code": "P038R031D007V0002", "district_code": "P038R031D007", "village": "Batumanumpak", "postal_code": [22472]}, {"village_code": "P038R031D007V0003", "district_code": "P038R031D007", "village": "Godung Borotan", "postal_code": [22472]}, {"village_code": "P038R031D007V0004", "district_code": "P038R031D007", "village": "Harianja", "postal_code": [22472]}, {"village_code": "P038R031D007V0005", "district_code": "P038R031D007", "village": "Hutaraja", "postal_code": [22472]}, {"village_code": "P038R031D007V0006", "district_code": "P038R031D007", "village": "Lumban SinagaSimatupang", "postal_code": [22472]}, {"village_code": "P038R031D007V0007", "district_code": "P038R031D007", "village": "Lumban Siregar", "postal_code": [22472]}, {"village_code": "P038R031D007V0008", "district_code": "P038R031D007", "village": "Najumambe", "postal_code": [22472]}, {"village_code": "P038R031D007V0009", "district_code": "P038R031D007", "village": "Padang Parsadaan", "postal_code": [22472]}, {"village_code": "P038R031D007V0010", "district_code": "P038R031D007", "village": "Pakpahan", "postal_code": [22472]}, {"village_code": "P038R031D007V0011", "district_code": "P038R031D007", "village": "Pansurnatolu", "postal_code": [22472]}, {"village_code": "P038R031D007V0012", "district_code": "P038R031D007", "village": "Parlombuan", "postal_code": [22472]}, {"village_code": "P038R031D007V0013", "district_code": "P038R031D007", "village": "Parratusan", "postal_code": [22472]}, {"village_code": "P038R031D007V0014", "district_code": "P038R031D007", "village": "Parsibarungan", "postal_code": [22472]}, {"village_code": "P038R031D007V0015", "district_code": "P038R031D007", "village": "Parsorminan I", "postal_code": [22472]}, {"village_code": "P038R031D007V0016", "district_code": "P038R031D007", "village": "Purbatua", "postal_code": [22472]}, {"village_code": "P038R031D007V0017", "district_code": "P038R031D007", "village": "Rahut Bosi", "postal_code": [22472]}, {"village_code": "P038R031D007V0018", "district_code": "P038R031D007", "village": "Rahut Bosi Onan", "postal_code": [22472]}, {"village_code": "P038R031D007V0019", "district_code": "P038R031D007", "village": "Sampagul", "postal_code": [22472]}, {"village_code": "P038R031D007V0020", "district_code": "P038R031D007", "village": "Sibingke", "postal_code": [22472]}, {"village_code": "P038R031D007V0021", "district_code": "P038R031D007", "village": "Sigotom Dolok Nauli", "postal_code": [22472]}, {"village_code": "P038R031D007V0022", "district_code": "P038R031D007", "village": "Sigotom Julu", "postal_code": [22472]}, {"village_code": "P038R031D007V0023", "district_code": "P038R031D007", "village": "Sigotom Timur", "postal_code": [22472]}, {"village_code": "P038R031D007V0024", "district_code": "P038R031D007", "village": "Silantom Jae", "postal_code": [22472]}, {"village_code": "P038R031D007V0025", "district_code": "P038R031D007", "village": "Silantom Julu", "postal_code": [22472]}, {"village_code": "P038R031D007V0026", "district_code": "P038R031D007", "village": "Silantom Tonga", "postal_code": [22472]}]}