{"district_code": "P038R017D004", "villages": [{"village_code": "P038R017D004V0001", "district_code": "P038R017D004", "village": "Bawofanayama", "postal_code": [22865]}, {"village_code": "P038R017D004V0002", "district_code": "P038R017D004", "village": "Bawomataluo", "postal_code": [22865]}, {"village_code": "P038R017D004V0003", "district_code": "P038R017D004", "village": "Bawonahono", "postal_code": [22865]}, {"village_code": "P038R017D004V0004", "district_code": "P038R017D004", "village": "Eho Orahili", "postal_code": [22865]}, {"village_code": "P038R017D004V0005", "district_code": "P038R017D004", "village": "Ete Batu", "postal_code": [22865]}, {"village_code": "P038R017D004V0006", "district_code": "P038R017D004", "village": "Hilifarokha Lawa", "postal_code": [22865]}, {"village_code": "P038R017D004V0007", "district_code": "P038R017D004", "village": "Hiligito", "postal_code": [22865]}, {"village_code": "P038R017D004V0008", "district_code": "P038R017D004", "village": "Hilikara Maha", "postal_code": [22865]}, {"village_code": "P038R017D004V0009", "district_code": "P038R017D004", "village": "Hilinawalo Fau", "postal_code": [22865]}, {"village_code": "P038R017D004V0010", "district_code": "P038R017D004", "village": "Hiliofonaluo", "postal_code": [22865]}, {"village_code": "P038R017D004V0011", "district_code": "P038R017D004", "village": "Hilisalawa", "postal_code": [22865]}, {"village_code": "P038R017D004V0012", "district_code": "P038R017D004", "village": "Hilizihono", "postal_code": [22865]}, {"village_code": "P038R017D004V0013", "district_code": "P038R017D004", "village": "Lahusa Fau", "postal_code": [22865]}, {"village_code": "P038R017D004V0014", "district_code": "P038R017D004", "village": "Onohondro", "postal_code": [22865]}, {"village_code": "P038R017D004V0015", "district_code": "P038R017D004", "village": "Orahili Fau", "postal_code": [22865]}, {"village_code": "P038R017D004V0016", "district_code": "P038R017D004", "village": "Siliwulawa", "postal_code": [22865]}, {"village_code": "P038R017D004V0017", "district_code": "P038R017D004", "village": "Siwalawa", "postal_code": [22865]}]}