{"district_code": "P038R031D006", "villages": [{"village_code": "P038R031D006V0001", "district_code": "P038R031D006", "village": "Huta Barat", "postal_code": [22463]}, {"village_code": "P038R031D006V0002", "district_code": "P038R031D006", "village": "Janji Natogu", "postal_code": [22463]}, {"village_code": "P038R031D006V0003", "district_code": "P038R031D006", "village": "Lobu Pining", "postal_code": [22463]}, {"village_code": "P038R031D006V0004", "district_code": "P038R031D006", "village": "Lontung Dolok", "postal_code": [22463]}, {"village_code": "P038R031D006V0005", "district_code": "P038R031D006", "village": "Lumban Dolok", "postal_code": [22463]}, {"village_code": "P038R031D006V0006", "district_code": "P038R031D006", "village": "Lumban Gaol", "postal_code": [22463]}, {"village_code": "P038R031D006V0007", "district_code": "P038R031D006", "village": "Lumban Garaga", "postal_code": [22463]}, {"village_code": "P038R031D006V0008", "district_code": "P038R031D006", "village": "Lumban Jaean", "postal_code": [22463]}, {"village_code": "P038R031D006V0009", "district_code": "P038R031D006", "village": "Lumban Tonga", "postal_code": [22463]}, {"village_code": "P038R031D006V0010", "district_code": "P038R031D006", "village": "Onan Hasang", "postal_code": [22463]}, {"village_code": "P038R031D006V0011", "district_code": "P038R031D006", "village": "Pagur Dotan", "postal_code": [22463]}, {"village_code": "P038R031D006V0012", "district_code": "P038R031D006", "village": "Pantis", "postal_code": [22463]}, {"village_code": "P038R031D006V0013", "district_code": "P038R031D006", "village": "Sibaganding", "postal_code": [22463]}, {"village_code": "P038R031D006V0014", "district_code": "P038R031D006", "village": "Simanampang", "postal_code": [22463]}, {"village_code": "P038R031D006V0015", "district_code": "P038R031D006", "village": "Simardangiang", "postal_code": [22463]}, {"village_code": "P038R031D006V0016", "district_code": "P038R031D006", "village": "Simasom", "postal_code": [22463]}, {"village_code": "P038R031D006V0017", "district_code": "P038R031D006", "village": "Simasom Toruan", "postal_code": [22463]}, {"village_code": "P038R031D006V0018", "district_code": "P038R031D006", "village": "Simataniari", "postal_code": [22463]}, {"village_code": "P038R031D006V0019", "district_code": "P038R031D006", "village": "Sitolu Ama", "postal_code": [22463]}]}